pyopv/__init__.py
pyopv/opvdicom/__init__.py
pyopv/opvdicom/dcm_defs.py
pyopv/opvdicom/tags.py
pyopv/opvdicom/components/__init__.py
pyopv/opvdicom/components/sensitivity.py
pyopv-0.1.2.2.dist-info/LICENSE
pyopv-0.1.2.2.dist-info/METADATA
pyopv-0.1.2.2.dist-info/WHEEL
pyopv-0.1.2.2.dist-info/top_level.txt
pyopv-0.1.2.2.dist-info/RECORD
