Metadata-Version: 2.1
Name: pyopv
Version: 0.1.2.2
Summary: This package provides a set of tools for checking OPV DICOM compliance and converting OPV DICOM to CSV or JSON.
Home-page: https://github.com/Shallaj/py-opv
Author: Shahin Hallaj, MD
Author-email: Shahin Hallaj <shallaj@health.ucsd.edu>
License: MIT License
Project-URL: Homepage, https://github.com/Shallaj/py-opv
Project-URL: Source, https://github.com/Shallaj/py-opv
Keywords: DICOM,OPV,CSV,JSON,Medical Imaging
Classifier: Programming Language :: Python :: 3
Classifier: License :: OSI Approved :: MIT License
Classifier: Operating System :: OS Independent
Requires-Python: >=3.8
License-File: LICENSE
Requires-Dist: pydicom
Requires-Dist: numpy
Requires-Dist: pandas
Requires-Dist: requests
